argumento/__init__.py
argumento/_version.py
argumento/namespace_dict.py
argumento/parsers.py
argumento-1.2.1.dist-info/LICENSE
argumento-1.2.1.dist-info/METADATA
argumento-1.2.1.dist-info/WHEEL
argumento-1.2.1.dist-info/top_level.txt
argumento-1.2.1.dist-info/RECORD
