Metadata-Version: 2.1
Name: argumento
Version: 1.2.1
Summary: Package for combining config and command-line args
Author-email: OK111 <oleg.khadartsev@gmail.com>
Project-URL: Homepage, https://github.com/OlegKhadartsev/config-args
Classifier: Programming Language :: Python :: 3
Classifier: License :: OSI Approved :: MIT License
Classifier: Operating System :: OS Independent
Requires-Python: >=3.7
License-File: LICENSE
Requires-Dist: toml >=0.10
Requires-Dist: PyYAML >=6.0
